weblite/__init__.py
weblite/adapters/__init__.py
weblite/adapters/source_element.py
weblite/adapters/source_page.py
weblite/adapters/playwright/__init__.py
weblite/adapters/playwright/element.py
weblite/adapters/playwright/page.py
weblite/elements/base.py
weblite/elements/constants.py
weblite/elements/display.py
weblite/elements/factory.py
weblite/elements/utils.py
weblite/elements/content/__init__.py
weblite/elements/content/base.py
weblite/elements/content/button.py
weblite/elements/content/svg.py
weblite/elements/content/textarea.py
weblite/elements/empty/base.py
weblite/elements/empty/img.py
weblite/elements/empty/input.py
weblite/selector/__init__.py
weblite/utils/__init__.py
weblite/utils/display_pruner.py
weblite/utils/formatting.py
weblite/utils/source_to_element.py
weblite/utils/visibility_filter.py
weblite-0.2.3.dist-info/licenses/LICENSE
weblite-0.2.3.dist-info/METADATA
weblite-0.2.3.dist-info/WHEEL
weblite-0.2.3.dist-info/top_level.txt
weblite-0.2.3.dist-info/RECORD
