Metadata-Version: 2.4
Name: weblite
Version: 0.2.3
Summary: A text-based web representation that retains meaningful structure information while displaying only human-visible content
Author-email: Steve Wang <stevewang.at.work@gmail.com>
License: MIT
Project-URL: Homepage, https://github.com/steve-z-wang/weblite
Project-URL: Issues, https://github.com/steve-z-wang/weblite/issues
Project-URL: Repository, https://github.com/steve-z-wang/weblite.git
Keywords: web-automation,playwright,llm,ai
Classifier: Development Status :: 3 - Alpha
Classifier: Intended Audience :: Developers
Classifier: License :: OSI Approved :: MIT License
Classifier: Programming Language :: Python :: 3
Classifier: Programming Language :: Python :: 3.8
Classifier: Programming Language :: Python :: 3.9
Classifier: Programming Language :: Python :: 3.10
Classifier: Programming Language :: Python :: 3.11
Requires-Python: >=3.8
License-File: LICENSE
Requires-Dist: playwright>=1.40.0
Provides-Extra: dev
Requires-Dist: pytest>=7.0; extra == "dev"
Requires-Dist: black; extra == "dev"
Requires-Dist: flake8; extra == "dev"
Dynamic: license-file
